alphacast_library/__init__.py
alphacast_library/alphacast.py
alphacast_library-0.1.4.dist-info/METADATA
alphacast_library-0.1.4.dist-info/WHEEL
alphacast_library-0.1.4.dist-info/top_level.txt
alphacast_library-0.1.4.dist-info/RECORD
