Metadata-Version: 2.1
Name: alphacast-library
Version: 0.1.4
Summary: Alphacast Python library
Home-page: https://alphacast-library.readthedocs.io/
Author: Alphacast.io
Author-email: hello@alphacast.io
License: MIT
Platform: UNKNOWN
Classifier: Intended Audience :: Developers
Classifier: License :: OSI Approved :: MIT License
Classifier: Programming Language :: Python
Classifier: Programming Language :: Python :: 3
Classifier: Programming Language :: Python :: 3.6
Classifier: Programming Language :: Python :: 3.7
Classifier: Programming Language :: Python :: 3.8
Classifier: Programming Language :: Python :: 3.9
Classifier: Operating System :: OS Independent
Requires-Dist: requests
Requires-Dist: pandas
